dxw/__init__.py
dxw/dxw.py
dxw-0.0.2.dist-info/LICENSE
dxw-0.0.2.dist-info/METADATA
dxw-0.0.2.dist-info/WHEEL
dxw-0.0.2.dist-info/top_level.txt
dxw-0.0.2.dist-info/RECORD
